pystiebeleltron/__init__.py
pystiebeleltron/lwz.py
pystiebeleltron/pystiebeleltron.py
pystiebeleltron/wpm.py
pystiebeleltron-0.2.3.dist-info/METADATA
pystiebeleltron-0.2.3.dist-info/WHEEL
pystiebeleltron-0.2.3.dist-info/licenses/LICENSE
pystiebeleltron-0.2.3.dist-info/RECORD
