Metadata-Version: 2.4
Name: pystiebeleltron
Version: 0.2.3
Summary: Python API for interacting with the Stiebel Eltron ISG web gateway via Modbus for controlling integral ventilation units and heat pumps.
Project-URL: Homepage, https://github.com/ThyMYthOS/python-stiebel-eltron
Project-URL: Issues, https://github.com/ThyMYthOS/python-stiebel-eltron/issues
Author: Manuel Stahl, Martin Fuchs
License: MIT License
License-File: LICENSE
Keywords: modbus,stiebel-eltron,tecalor
Classifier: Programming Language :: Python :: 3.10
Classifier: Programming Language :: Python :: 3.11
Classifier: Programming Language :: Python :: 3.12
Classifier: Programming Language :: Python :: 3.13
Requires-Python: <4,>=3.10
Requires-Dist: pymodbus<4,>=3.10.0
Provides-Extra: dev
Requires-Dist: jinja2>=3.1.6; extra == 'dev'
Requires-Dist: pytest-asyncio>=0.26.0; extra == 'dev'
Requires-Dist: pytest-mock>=3.14.0; extra == 'dev'
Requires-Dist: pytest>=8.3.5; extra == 'dev'
Requires-Dist: ruff>=0.12.0; extra == 'dev'
